{"id":"ZRoM","dependencies":[{"name":"/Users/preigile/Repos/shri/very-smart-house/package.json","includedInParent":true,"mtime":1538680745879},{"name":"/Users/preigile/Repos/shri/very-smart-house/.babelrc","includedInParent":true,"mtime":1538680745876}],"generated":{"js":"\"use strict\";Object.defineProperty(exports,\"__esModule\",{value:!0}),window.header={visibleNav:!1,displayNav:function(){window.header.visibleNav=!window.header.visibleNav,window.update()}},exports.default=function(){return'<div class=\"header\">\\n                <h3 class=\"header__logo\"></h3>\\n                <div class=\"header__menu\" onclick=\"header.displayNav()\"></div>\\n                <nav class=\"header__nav '+(header.visibleNav?\"header__nav_visible\":\"\")+'\">\\n                    <a class=\"header__nav-item header__nav-item_selected\" href=\"#\" target=\"_self\" onclick=\"header.displayNav()\">Сводка</a>\\n                    <a class=\"header__nav-item\" href=\"#\" target=\"_self\" onclick=\"header.displayNav()\">Устройства</a>\\n                    <a class=\"header__nav-item\" href=\"#\" target=\"_self\" onclick=\"header.displayNav()\">Сценарии</a>\\n                </nav>\\n            </div>'};","map":{"mappings":[{"source":"app/components/Header.js","original":{"line":20,"column":1},"generated":{"line":1,"column":0}},{"source":"app/components/Header.js","original":{"line":20,"column":1},"generated":{"line":1,"column":13}},{"source":"app/components/Header.js","original":{"line":20,"column":1},"generated":{"line":1,"column":20}},{"source":"app/components/Header.js","original":{"line":20,"column":1},"generated":{"line":1,"column":35}},{"source":"app/components/Header.js","original":{"line":20,"column":1},"generated":{"line":1,"column":43}},{"source":"app/components/Header.js","original":{"line":20,"column":1},"generated":{"line":1,"column":56}},{"source":"app/components/Header.js","original":{"line":20,"column":1},"generated":{"line":1,"column":57}},{"source":"app/components/Header.js","original":{"line":20,"column":1},"generated":{"line":1,"column":64}},{"source":"app/components/Header.js","name":"window","original":{"line":1,"column":0},"generated":{"line":1,"column":68}},{"source":"app/components/Header.js","name":"header","original":{"line":1,"column":7},"generated":{"line":1,"column":75}},{"source":"app/components/Header.js","original":{"line":1,"column":16},"generated":{"line":1,"column":82}},{"source":"app/components/Header.js","original":{"line":2,"column":16},"generated":{"line":1,"column":83}},{"source":"app/components/Header.js","original":{"line":2,"column":16},"generated":{"line":1,"column":95}},{"source":"app/components/Header.js","original":{"line":4,"column":16},"generated":{"line":1,"column":97}},{"source":"app/components/Header.js","original":{"line":4,"column":16},"generated":{"line":1,"column":108}},{"source":"app/components/Header.js","name":"header","original":{"line":5,"column":15},"generated":{"line":1,"column":119}},{"source":"app/components/Header.js","name":"header","original":{"line":5,"column":15},"generated":{"line":1,"column":126}},{"source":"app/components/Header.js","name":"visibleNav","original":{"line":5,"column":22},"generated":{"line":1,"column":133}},{"source":"app/components/Header.js","name":"window","original":{"line":5,"column":36},"generated":{"line":1,"column":145}},{"source":"app/components/Header.js","name":"header","original":{"line":5,"column":43},"generated":{"line":1,"column":152}},{"source":"app/components/Header.js","name":"visibleNav","original":{"line":5,"column":50},"generated":{"line":1,"column":159}},{"source":"app/components/Header.js","name":"update","original":{"line":6,"column":15},"generated":{"line":1,"column":170}},{"source":"app/components/Header.js","name":"update","original":{"line":6,"column":15},"generated":{"line":1,"column":177}},{"source":"app/components/Header.js","original":{"line":10,"column":15},"generated":{"line":1,"column":188}},{"source":"app/components/Header.js","original":{"line":10,"column":15},"generated":{"line":1,"column":196}},{"source":"app/components/Header.js","original":{"line":10,"column":15},"generated":{"line":1,"column":204}},{"source":"app/components/Header.js","name":"header","original":{"line":14,"column":42},"generated":{"line":1,"column":215}},{"source":"app/components/Header.js","name":"header","original":{"line":14,"column":42},"generated":{"line":1,"column":221}},{"source":"app/components/Header.js","name":"header","original":{"line":14,"column":42},"generated":{"line":1,"column":415}},{"source":"app/components/Header.js","name":"visibleNav","original":{"line":14,"column":49},"generated":{"line":1,"column":422}},{"source":"app/components/Header.js","original":{"line":14,"column":62},"generated":{"line":1,"column":433}},{"source":"app/components/Header.js","original":{"line":14,"column":86},"generated":{"line":1,"column":455}},{"source":"app/components/Header.js","original":{"line":11,"column":4},"generated":{"line":1,"column":459}}],"sources":{"app/components/Header.js":"window.header = {\n    visibleNav: false,\n\n    displayNav: () => {\n        window.header.visibleNav = !window.header.visibleNav;\n        window.update();\n    }\n};\n\nexport default () => {\n    return `<div class=\"header\">\n                <h3 class=\"header__logo\"></h3>\n                <div class=\"header__menu\" onclick=\"header.displayNav()\"></div>\n                <nav class=\"header__nav ${header.visibleNav ? 'header__nav_visible' : ''}\">\n                    <a class=\"header__nav-item header__nav-item_selected\" href=\"#\" target=\"_self\" onclick=\"header.displayNav()\">Сводка</a>\n                    <a class=\"header__nav-item\" href=\"#\" target=\"_self\" onclick=\"header.displayNav()\">Устройства</a>\n                    <a class=\"header__nav-item\" href=\"#\" target=\"_self\" onclick=\"header.displayNav()\">Сценарии</a>\n                </nav>\n            </div>`\n}\n"},"lineCount":null}},"hash":"29a46e70bb21636b1c62d328714ef0ca","cacheData":{"env":{}}}