{"id":"Lent","dependencies":[{"name":"/Users/preigile/Repos/shri/very-smart-house/package.json","includedInParent":true,"mtime":1538576794443},{"name":"/Users/preigile/Repos/shri/very-smart-house/.babelrc","includedInParent":true,"mtime":1538576499902},{"name":"./styles/main.less","loc":{"line":1,"column":7},"parent":"/Users/preigile/Repos/shri/very-smart-house/app/app.js","resolved":"/Users/preigile/Repos/shri/very-smart-house/app/styles/main.less"}],"generated":{"js":"\"use strict\";require(\"./styles/main.less\"),console.log(\"smart house detected\");","map":{"mappings":[{"source":"app/app.js","original":{"line":3,"column":0},"generated":{"line":1,"column":0}},{"source":"app/app.js","original":{"line":1,"column":0},"generated":{"line":1,"column":13}},{"source":"app/app.js","original":{"line":1,"column":0},"generated":{"line":1,"column":21}},{"source":"app/app.js","name":"console","original":{"line":3,"column":0},"generated":{"line":1,"column":43}},{"source":"app/app.js","name":"log","original":{"line":3,"column":8},"generated":{"line":1,"column":51}},{"source":"app/app.js","original":{"line":3,"column":12},"generated":{"line":1,"column":55}}],"sources":{"app/app.js":"import './styles/main.less';\n\nconsole.log('smart house detected');"},"lineCount":null}},"hash":"2feb03b5695ec62f8effa84fd37180da","cacheData":{"env":{}}}